aicv/__init__.py
aicv/async_client.py
aicv/cli.py
aicv/client.py
aicv/exceptions.py
aicv/resources/__init__.py
aicv/resources/optimization.py
aicv/resources/resume.py
aicv/resources/session.py
aicv/types/__init__.py
aicv/types/optimization.py
aicv/types/resume.py
aicv/types/session.py
tests/__init__.py
tests/example.py
aicv_python-0.1.4.dist-info/LICENSE
aicv_python-0.1.4.dist-info/METADATA
aicv_python-0.1.4.dist-info/WHEEL
aicv_python-0.1.4.dist-info/entry_points.txt
aicv_python-0.1.4.dist-info/top_level.txt
aicv_python-0.1.4.dist-info/RECORD
