Metadata-Version: 2.1
Name: aicv-python
Version: 0.1.4
Summary: AiCV Python SDK - AI-powered CV analysis and generation toolkit
Home-page: https://github.com/AIGility-Cloud-Innovation/aicv-python
Author: AIGility Cloud Innovation
Author-email: contact@aigility.com
License: UNKNOWN
Platform: UNKNOWN
Classifier: Development Status :: 4 - Beta
Classifier: Intended Audience :: Developers
Classifier: License :: OSI Approved :: MIT License
Classifier: Operating System :: OS Independent
Classifier: Programming Language :: Python :: 3
Classifier: Programming Language :: Python :: 3.8
Classifier: Programming Language :: Python :: 3.9
Classifier: Programming Language :: Python :: 3.10
Classifier: Programming Language :: Python :: 3.11
Classifier: Programming Language :: Python :: 3.12
Classifier: Topic :: Software Development :: Libraries :: Python Modules
Classifier: Topic :: Scientific/Engineering :: Artificial Intelligence
Classifier: Topic :: Text Processing :: Linguistic
Requires-Python: >=3.8
Requires-Dist: requests (>=2.28.0)
Requires-Dist: pydantic (>=2.0.0)
Requires-Dist: httpx (>=0.24.0)
Requires-Dist: typing-extensions (>=4.0.0)
Provides-Extra: dev
Requires-Dist: pytest (>=7.0.0) ; extra == 'dev'
Requires-Dist: pytest-cov (>=4.0.0) ; extra == 'dev'
Requires-Dist: black (>=22.0.0) ; extra == 'dev'
Requires-Dist: isort (>=5.0.0) ; extra == 'dev'
Requires-Dist: flake8 (>=5.0.0) ; extra == 'dev'
Requires-Dist: mypy (>=1.0.0) ; extra == 'dev'
Requires-Dist: pre-commit (>=2.20.0) ; extra == 'dev'
Provides-Extra: docs
Requires-Dist: sphinx (>=5.0.0) ; extra == 'docs'
Requires-Dist: sphinx-rtd-theme (>=1.0.0) ; extra == 'docs'
Requires-Dist: myst-parser (>=0.18.0) ; extra == 'docs'
